examples/__init__.py
examples/e_filter_by.py
sqlalchemy_core_catalyst-1.0.1.dist-info/METADATA
sqlalchemy_core_catalyst-1.0.1.dist-info/WHEEL
sqlalchemy_core_catalyst-1.0.1.dist-info/top_level.txt
sqlalchemy_core_catalyst-1.0.1.dist-info/RECORD
