Metadata-Version: 2.1
Name: sqlalchemy-core-catalyst
Version: 1.0.1
Summary: Library for easy interaction with SQLAlchemy and Pydantic.
Requires-Dist: greenlet ==3.0.1
Requires-Dist: pydantic ==1.10.2
Requires-Dist: SQLAlchemy ==1.4.25
Requires-Dist: typing-extensions ==4.8.0
